odoo/addons/sale_order_import_ubl_line_customer_ref/README.rst
odoo/addons/sale_order_import_ubl_line_customer_ref/__init__.py
odoo/addons/sale_order_import_ubl_line_customer_ref/__manifest__.py
odoo/addons/sale_order_import_ubl_line_customer_ref/i18n/es.po
odoo/addons/sale_order_import_ubl_line_customer_ref/i18n/it.po
odoo/addons/sale_order_import_ubl_line_customer_ref/i18n/sale_order_import_ubl_line_customer_ref.pot
odoo/addons/sale_order_import_ubl_line_customer_ref/readme/CONTRIBUTORS.md
odoo/addons/sale_order_import_ubl_line_customer_ref/readme/DESCRIPTION.md
odoo/addons/sale_order_import_ubl_line_customer_ref/static/description/icon.png
odoo/addons/sale_order_import_ubl_line_customer_ref/static/description/index.html
odoo/addons/sale_order_import_ubl_line_customer_ref/tests/__init__.py
odoo/addons/sale_order_import_ubl_line_customer_ref/tests/test_order_line_customer_ref.py
odoo/addons/sale_order_import_ubl_line_customer_ref/wizard/__init__.py
odoo/addons/sale_order_import_ubl_line_customer_ref/wizard/sale_order_import.py
odoo_addon_sale_order_import_ubl_line_customer_ref-18.0.1.0.0.3.dist-info/METADATA
odoo_addon_sale_order_import_ubl_line_customer_ref-18.0.1.0.0.3.dist-info/WHEEL
odoo_addon_sale_order_import_ubl_line_customer_ref-18.0.1.0.0.3.dist-info/top_level.txt
odoo_addon_sale_order_import_ubl_line_customer_ref-18.0.1.0.0.3.dist-info/RECORD
